[
  {
    "_id": "6439713c1d8869133e8881ea",
    "name": "Demo Customer 1",
    "email": "customer1@example.com",
    "phone": "+88018000001",
    "image": "",
    "address": "Demo Address 1, Dhaka",
    "city": "Dhaka",
    "country": "Bangladesh"
  },
  {
    "_id": "6439713c1d8869133e8881e3",
    "name": "Demo Customer 2",
    "email": "customer2@example.com",
    "phone": "+88018000002",
    "image": "",
    "address": "Demo Address 2, Dhaka",
    "city": "Dhaka",
    "country": "Bangladesh"
  },
  {
    "_id": "6439713c1d8869133e8881eb",
    "name": "Demo Customer 3",
    "email": "customer3@example.com",
    "phone": "+88018000003",
    "image": "",
    "address": "Demo Address 3, Dhaka",
    "city": "Dhaka",
    "country": "Bangladesh"
  },
  {
    "_id": "6439713c1d8869133e8881f4",
    "name": "Demo Customer 4",
    "email": "customer4@example.com",
    "phone": "+88018000004",
    "image": "",
    "address": "Demo Address 4, Dhaka",
    "city": "Dhaka",
    "country": "Bangladesh"
  },
  {
    "_id": "6439713c1d8869133e8881f2",
    "name": "Demo Customer 5",
    "email": "customer5@example.com",
    "phone": "+88018000005",
    "image": "",
    "address": "Demo Address 5, Dhaka",
    "city": "Dhaka",
    "country": "Bangladesh"
  },
  {
    "_id": "6439713c1d8869133e8881f1",
    "name": "Demo Customer 6",
    "email": "customer6@example.com",
    "phone": "+88018000006",
    "image": "",
    "address": "Demo Address 6, Dhaka",
    "city": "Dhaka",
    "country": "Bangladesh"
  },
  {
    "_id": "6439713c1d8869133e8881f6",
    "name": "Demo Customer 7",
    "email": "customer7@example.com",
    "phone": "+88018000007",
    "image": "",
    "address": "Demo Address 7, Dhaka",
    "city": "Dhaka",
    "country": "Bangladesh"
  },
  {
    "_id": "6439713c1d8869133e8881e6",
    "name": "Demo Customer 8",
    "email": "customer8@example.com",
    "phone": "+88018000008",
    "image": "",
    "address": "Demo Address 8, Dhaka",
    "city": "Dhaka",
    "country": "Bangladesh"
  },
  {
    "_id": "6439713c1d8869133e8881ed",
    "name": "Demo Customer 9",
    "email": "customer9@example.com",
    "phone": "+88018000009",
    "image": "",
    "address": "Demo Address 9, Dhaka",
    "city": "Dhaka",
    "country": "Bangladesh"
  },
  {
    "_id": "6439713c1d8869133e8881f5",
    "name": "Demo Customer 10",
    "email": "customer10@example.com",
    "phone": "+88018000010",
    "image": "",
    "address": "Demo Address 10, Dhaka",
    "city": "Dhaka",
    "country": "Bangladesh"
  },
  {
    "_id": "6439713c1d8869133e8881e4",
    "name": "Demo Customer 11",
    "email": "customer11@example.com",
    "phone": "+88018000011",
    "image": "",
    "address": "Demo Address 11, Dhaka",
    "city": "Dhaka",
    "country": "Bangladesh"
  },
  {
    "_id": "6439713c1d8869133e8881ec",
    "name": "Demo Customer 12",
    "email": "customer12@example.com",
    "phone": "+88018000012",
    "image": "",
    "address": "Demo Address 12, Dhaka",
    "city": "Dhaka",
    "country": "Bangladesh"
  },
  {
    "_id": "6439713c1d8869133e8881e9",
    "name": "Demo Customer 13",
    "email": "customer13@example.com",
    "phone": "+88018000013",
    "address": "Demo Address 13, Dhaka",
    "image": "",
    "city": "Dhaka",
    "country": "Bangladesh"
  },
  {
    "_id": "6439713c1d8869133e8881ee",
    "name": "Demo Customer 14",
    "email": "customer14@example.com",
    "phone": "+88018000014",
    "image": "",
    "address": "Demo Address 14, Dhaka",
    "city": "Dhaka",
    "country": "Bangladesh"
  },
  {
    "_id": "6439713c1d8869133e8881e7",
    "name": "Demo Customer 15",
    "email": "customer15@example.com",
    "phone": "+88018000015",
    "image": "",
    "address": "Demo Address 15, Dhaka",
    "city": "Dhaka",
    "country": "Bangladesh"
  },
  {
    "_id": "6439713c1d8869133e8881f3",
    "name": "Demo Customer 16",
    "email": "customer16@example.com",
    "phone": "+88018000016",
    "image": "",
    "address": "Demo Address 16, Dhaka",
    "city": "Dhaka",
    "country": "Bangladesh"
  },
  {
    "_id": "6439713c1d8869133e8881f0",
    "name": "Demo Customer 17",
    "email": "customer17@example.com",
    "phone": "+88018000017",
    "image": "",
    "address": "Demo Address 17, Dhaka",
    "city": "Dhaka",
    "country": "Bangladesh"
  },
  {
    "_id": "6439713c1d8869133e8881e5",
    "name": "Demo Customer 18",
    "email": "customer18@example.com",
    "phone": "+88018000018",
    "image": "",
    "address": "Demo Address 18, Dhaka",
    "city": "Dhaka",
    "country": "Bangladesh"
  },
  {
    "_id": "6439713c1d8869133e8881e8",
    "name": "Demo Customer 19",
    "email": "customer19@example.com",
    "phone": "+88018000019",
    "image": "",
    "address": "Demo Address 19, Dhaka",
    "city": "Dhaka",
    "country": "Bangladesh"
  },
  {
    "_id": "6439713c1d8869133e8881ef",
    "name": "Demo Customer 20",
    "email": "customer20@example.com",
    "phone": "+88018000020",
    "image": "",
    "address": "Demo Address 20, Dhaka",
    "city": "Dhaka",
    "country": "Bangladesh"
  },
  {
    "_id": "69aefa820415c443adea038d",
    "name": "Demo Customer 21",
    "email": "customer21@example.com",
    "shippingAddress": {
      "name": "Demo Customer 21",
      "address": "Demo Address 21, Dhaka",
      "contact": "+88018000021",
      "country": "Bangladesh",
      "city": "Dhaka",
      "area": "Gulshan",
      "email": "customer21@example.com",
      "zipCode": "1200"
    },
    "phone": "+88018000021",
    "image": "",
    "address": "Demo Address 21, Dhaka",
    "city": "Dhaka",
    "country": "Bangladesh"
  },
  {
    "_id": "69af077f55e9c79a176bdcc4",
    "name": "Demo Customer 22",
    "image": "",
    "email": "customer22@example.com",
    "shippingAddress": {
      "name": "Demo Customer 22",
      "address": "Demo Address 22, Dhaka",
      "contact": "+88018000022",
      "country": "Bangladesh",
      "city": "Dhaka",
      "area": "Old Dhaka",
      "email": "customer22@example.com",
      "zipCode": "1200"
    },
    "phone": "+88018000022",
    "address": "Demo Address 22, Dhaka",
    "city": "Dhaka",
    "country": "Bangladesh"
  },
  {
    "_id": "69b265a2ed9245cbe6eebf5d",
    "name": "Demo Customer 23",
    "email": "customer23@example.com",
    "shippingAddress": {
      "name": "Demo Customer 23",
      "address": "Demo Address 23, Dhaka",
      "contact": "+88018000023",
      "country": "Bangladesh",
      "city": "Dhaka",
      "area": "Mirpur",
      "email": "customer23@example.com",
      "zipCode": "1200"
    },
    "phone": "+88018000023",
    "image": "",
    "address": "Demo Address 23, Dhaka",
    "city": "Dhaka",
    "country": "Bangladesh"
  },
  {
    "_id": "69b51b9eed9245cbe6ef48d9",
    "name": "Demo Customer 24",
    "email": "customer24@example.com",
    "address": "Demo Address 24, Dhaka",
    "image": "",
    "phone": "+88018000024",
    "shippingAddress": {
      "name": "Demo Customer 24",
      "address": "Demo Address 24, Dhaka",
      "contact": "+88018000024",
      "country": "Bangladesh",
      "city": "Dhaka",
      "area": "Mirpur",
      "email": "customer24@example.com",
      "zipCode": "1200"
    },
    "city": "Dhaka",
    "country": "Bangladesh"
  },
  {
    "_id": "69b52824ed9245cbe6ef50b8",
    "name": "Demo Customer 25",
    "email": "customer25@example.com",
    "shippingAddress": {
      "name": "Demo Customer 25",
      "contact": "+88018000025",
      "email": "customer25@example.com",
      "address": "Demo Address 25, Dhaka",
      "country": "Bangladesh",
      "city": "Dhaka",
      "zipCode": "1200"
    },
    "phone": "+88018000025",
    "image": "",
    "address": "Demo Address 25, Dhaka",
    "city": "Dhaka",
    "country": "Bangladesh"
  }
]
